mp1/src/top.v
// Cause yosys to throw an error when we implicitly declare nets
`default_nettype none

// Simulation timestep
`timescale 1ns / 10ps

module top (
    input  clk,
    output RGB_B,
    output RGB_G,
    output RGB_R
);

  localparam TIMER_CYCLES = 2000000;
  reg [$clog2(TIMER_CYCLES) - 1:0] count;

  reg [2:0] cycle_pos;
  reg [2:0] LEDS;

  initial begin
    LEDS = 3'b000;
    cycle_pos = 0;
    count = 0;
  end

  always @(posedge clk) begin
    if (count == TIMER_CYCLES - 1) begin

      if (cycle_pos == 5) begin
        cycle_pos <= 0;
      end else begin
        cycle_pos <= cycle_pos + 1;
      end

      count <= 0;

    end else begin
      count <= count + 1;
    end


  end

  always @(posedge clk) begin
    case (cycle_pos)
      3'd0: LEDS <= 3'b100;
      3'd1: LEDS <= 3'b110;
      3'd2: LEDS <= 3'b010;
      3'd3: LEDS <= 3'b011;
      3'd4: LEDS <= 3'b001;
      3'd5: LEDS <= 3'b101;
      default: LEDS <= 3'b000;
    endcase
  end

  assign RGB_R = ~LEDS[2];
  assign RGB_G = ~LEDS[1];
  assign RGB_B = ~LEDS[0];

endmodule

mp1/top.vcd
$date
	Mon Sep  8 19:36:03 2025
$end
$version
	Icarus Verilog
$end
$timescale
	10ps
$end
$scope module top $end
$var wire 1 ! RGB_B $end
$var wire 1 " RGB_G $end
$var wire 1 # RGB_R $end
$var wire 1 $ clk $end
$var parameter 32 % TIMER_CYCLES $end
$var reg 3 & LEDS [2:0] $end
$var reg 11 ' count [10:0] $end
$var reg 3 ( cycle_pos [2:0] $end
$upscope $end
$enddefinitions $end
$comment Show the parameter values. $end
$dumpall
b11111010000 %
$end
#0
$dumpvars
b0 (
b1 '
b100 &
1$
1#
1"
0!
$end
#4165
0$
#8330
b10 '
1$
#12495
0$
#16660
b11 '
1$
#20825
0$
#24990
b100 '
1$
#29155
0$
#33320
b101 '
1$
#37485
0$
#41650
b110 '
1$
#45815
0$
#49980
b111 '
1$
#54145
0$
#58310
b1000 '
1$
#62475
0$
#66640
b1001 '
1$
#70805
0$
#74970
b1010 '
1$
#79135
0$
#83300
b1011 '
1$
#87465
0$
#91630
b1100 '
1$
#95795
0$
#99960
b1101 '
1$
#104125
0$
#108290
b1110 '
1$
#112455
0$
#116620
b1111 '
1$
#120785
0$
#124950
b10000 '
1$
#129115
0$
#133280
b10001 '
1$
#137445
0$
#141610
b10010 '
1$
#145775
0$
#149940
b10011 '
1$
#154105
0$
#158270
b10100 '
1$
#162435
0$
#166600
b10101 '
1$
#170765
0$
#174930
b10110 '
1$
#179095
0$
#183260
b10111 '
1$
#187425
0$
#191590
b11000 '
1$
#195755
0$
#199920
b11001 '
1$
#204085
0$
#208250
b11010 '
1$
#212415
0$
#216580
b11011 '
1$
#220745
0$
#224910
b11100 '
1$
#229075
0$
#233240
b11101 '
1$
#237405
0$
#241570
b11110 '
1$
#245735
0$
#249900
b11111 '
1$
#254065
0$
#258230
b100000 '
1$
#262395
0$
#266560
b100001 '
1$
#270725
0$
#274890
b100010 '
1$
#279055
0$
#283220
b100011 '
1$
#287385
0$
#291550
b100100 '
1$
#295715
0$
#299880
b100101 '
1$
#304045
0$
#308210
b100110 '
1$
#312375
0$
#316540
b100111 '
1$
#320705
0$
#324870
b101000 '
1$
#329035
0$
#333200
b101001 '
1$
#337365
0$
#341530
b101010 '
1$
#345695
0$
#349860
b101011 '
1$
#354025
0$
#358190
b101100 '
1$
#362355
0$
#366520
b101101 '
1$
#370685
0$
#374850
b101110 '
1$
#379015
0$
#383180
b101111 '
1$
#387345
0$
#391510
b110000 '
1$
#395675
0$
#399840
b110001 '
1$
#404005
0$
#408170
b110010 '
1$
#412335
0$
#416500
b110011 '
1$
#420665
0$
#424830
b110100 '
1$
#428995
0$
#433160
b110101 '
1$
#437325
0$
#441490
b110110 '
1$
#445655
0$
#449820
b110111 '
1$
#453985
0$
#458150
b111000 '
1$
#462315
0$
#466480
b111001 '
1$
#470645
0$
#474810
b111010 '
1$
#478975
0$
#483140
b111011 '
1$
#487305
0$
#491470
b111100 '
1$
#495635
0$
#499800
b111101 '
1$
#503965
0$
#508130
b111110 '
1$
#512295
0$
#516460
b111111 '
1$
#520625
0$
#524790
b1000000 '
1$
#528955
0$
#533120
b1000001 '
1$
#537285
0$
#541450
b1000010 '
1$
#545615
0$
#549780
b1000011 '
1$
#553945
0$
#558110
b1000100 '
1$
#562275
0$
#566440
b1000101 '
1$
#570605
0$
#574770
b1000110 '
1$
#578935
0$
#583100
b1000111 '
1$
#587265
0$
#591430
b1001000 '
1$
#595595
0$
#599760
b1001001 '
1$
#603925
0$
#608090
b1001010 '
1$
#612255
0$
#616420
b1001011 '
1$
#620585
0$
#624750
b1001100 '
1$
#628915
0$
#633080
b1001101 '
1$
#637245
0$
#641410
b1001110 '
1$
#645575
0$
#649740
b1001111 '
1$
#653905
0$
#658070
b1010000 '
1$
#662235
0$
#666400
b1010001 '
1$
#670565
0$
#674730
b1010010 '
1$
#678895
0$
#683060
b1010011 '
1$
#687225
0$
#691390
b1010100 '
1$
#695555
0$
#699720
b1010101 '
1$
#703885
0$
#708050
b1010110 '
1$
#712215
0$
#716380
b1010111 '
1$
#720545
0$
#724710
b1011000 '
1$
#728875
0$
#733040
b1011001 '
1$
#737205
0$
#741370
b1011010 '
1$
#745535
0$
#749700
b1011011 '
1$
#753865
0$
#758030
b1011100 '
1$
#762195
0$
#766360
b1011101 '
1$
#770525
0$
#774690
b1011110 '
1$
#778855
0$
#783020
b1011111 '
1$
#787185
0$
#791350
b1100000 '
1$
#795515
0$
#799680
b1100001 '
1$
#803845
0$
#808010
b1100010 '
1$
#812175
0$
#816340
b1100011 '
1$
#820505
0$
#824670
b1100100 '
1$
#828835
0$
#833000
b1100101 '
1$
#837165
0$
#841330
b1100110 '
1$
#845495
0$
#849660
b1100111 '
1$
#853825
0$
#857990
b1101000 '
1$
#862155
0$
#866320
b1101001 '
1$
#870485
0$
#874650
b1101010 '
1$
#878815
0$
#882980
b1101011 '
1$
#887145
0$
#891310
b1101100 '
1$
#895475
0$
#899640
b1101101 '
1$
#903805
0$
#907970
b1101110 '
1$
#912135
0$
#916300
b1101111 '
1$
#920465
0$
#924630
b1110000 '
1$
#928795
0$
#932960
b1110001 '
1$
#937125
0$
#941290
b1110010 '
1$
#945455
0$
#949620
b1110011 '
1$
#953785
0$
#957950
b1110100 '
1$
#962115
0$
#966280
b1110101 '
1$
#970445
0$
#974610
b1110110 '
1$
#978775
0$
#982940
b1110111 '
1$
#987105
0$
#991270
b1111000 '
1$
#995435
0$
#999600
b1111001 '
1$
#1003765
0$
#1007930
b1111010 '
1$
#1012095
0$
#1016260
b1111011 '
1$
#1020425
0$
#1024590
b1111100 '
1$
#1028755
0$
#1032920
b1111101 '
1$
#1037085
0$
#1041250
b1111110 '
1$
#1045415
0$
#1049580
b1111111 '
1$
#1053745
0$
#1057910
b10000000 '
1$
#1062075
0$
#1066240
b10000001 '
1$
#1070405
0$
#1074570
b10000010 '
1$
#1078735
0$
#1082900
b10000011 '
1$
#1087065
0$
#1091230
b10000100 '
1$
#1095395
0$
#1099560
b10000101 '
1$
#1103725
0$
#1107890
b10000110 '
1$
#1112055
0$
#1116220
b10000111 '
1$
#1120385
0$
#1124550
b10001000 '
1$
#1128715
0$
#1132880
b10001001 '
1$
#1137045
0$
#1141210
b10001010 '
1$
#1145375
0$
#1149540
b10001011 '
1$
#1153705
0$
#1157870
b10001100 '
1$
#1162035
0$
#1166200
b10001101 '
1$
#1170365
0$
#1174530
b10001110 '
1$
#1178695
0$
#1182860
b10001111 '
1$
#1187025
0$
#1191190
b10010000 '
1$
#1195355
0$
#1199520
b10010001 '
1$
#1203685
0$
#1207850
b10010010 '
1$
#1212015
0$
#1216180
b10010011 '
1$
#1220345
0$
#1224510
b10010100 '
1$
#1228675
0$
#1232840
b10010101 '
1$
#1237005
0$
#1241170
b10010110 '
1$
#1245335
0$
#1249500
b10010111 '
1$
#1253665
0$
#1257830
b10011000 '
1$
#1261995
0$
#1266160
b10011001 '
1$
#1270325
0$
#1274490
b10011010 '
1$
#1278655
0$
#1282820
b10011011 '
1$
#1286985
0$
#1291150
b10011100 '
1$
#1295315
0$
#1299480
b10011101 '
1$
#1303645
0$
#1307810
b10011110 '
1$
#1311975
0$
#1316140
b10011111 '
1$
#1320305
0$
#1324470
b10100000 '
1$
#1328635
0$
#1332800
b10100001 '
1$
#1336965
0$
#1341130
b10100010 '
1$
#1345295
0$
#1349460
b10100011 '
1$
#1353625
0$
#1357790
b10100100 '
1$
#1361955
0$
#1366120
b10100101 '
1$
#1370285
0$
#1374450
b10100110 '
1$
#1378615
0$
#1382780
b10100111 '
1$
#1386945
0$
#1391110
b10101000 '
1$
#1395275
0$
#1399440
b10101001 '
1$
#1403605
0$
#1407770
b10101010 '
1$
#1411935
0$
#1416100
b10101011 '
1$
#1420265
0$
#1424430
b10101100 '
1$
#1428595
0$
#1432760
b10101101 '
1$
#1436925
0$
#1441090
b10101110 '
1$
#1445255
0$
#1449420
b10101111 '
1$
#1453585
0$
#1457750
b10110000 '
1$
#1461915
0$
#1466080
b10110001 '
1$
#1470245
0$
#1474410
b10110010 '
1$
#1478575
0$
#1482740
b10110011 '
1$
#1486905
0$
#1491070
b10110100 '
1$
#1495235
0$
#1499400
b10110101 '
1$
#1503565
0$
#1507730
b10110110 '
1$
#1511895
0$
#1516060
b10110111 '
1$
#1520225
0$
#1524390
b10111000 '
1$
#1528555
0$
#1532720
b10111001 '
1$
#1536885
0$
#1541050
b10111010 '
1$
#1545215
0$
#1549380
b10111011 '
1$
#1553545
0$
#1557710
b10111100 '
1$
#1561875
0$
#1566040
b10111101 '
1$
#1570205
0$
#1574370
b10111110 '
1$
#1578535
0$
#1582700
b10111111 '
1$
#1586865
0$
#1591030
b11000000 '
1$
#1595195
0$
#1599360
b11000001 '
1$
#1603525
0$
#1607690
b11000010 '
1$
#1611855
0$
#1616020
b11000011 '
1$
#1620185
0$
#1624350
b11000100 '
1$
#1628515
0$
#1632680
b11000101 '
1$
#1636845
0$
#1641010
b11000110 '
1$
#1645175
0$
#1649340
b11000111 '
1$
#1653505
0$
#1657670
b11001000 '
1$
#1661835
0$
#1666000
b11001001 '
1$
#1670165
0$
#1674330
b11001010 '
1$
#1678495
0$
#1682660
b11001011 '
1$
#1686825
0$
#1690990
b11001100 '
1$
#1695155
0$
#1699320
b11001101 '
1$
#1703485
0$
#1707650
b11001110 '
1$
#1711815
0$
#1715980
b11001111 '
1$
#1720145
0$
#1724310
b11010000 '
1$
#1728475
0$
#1732640
b11010001 '
1$
#1736805
0$
#1740970
b11010010 '
1$
#1745135
0$
#1749300
b11010011 '
1$
#1753465
0$
#1757630
b11010100 '
1$
#1761795
0$
#1765960
b11010101 '
1$
#1770125
0$
#1774290
b11010110 '
1$
#1778455
0$
#1782620
b11010111 '
1$
#1786785
0$
#1790950
b11011000 '
1$
#1795115
0$
#1799280
b11011001 '
1$
#1803445
0$
#1807610
b11011010 '
1$
#1811775
0$
#1815940
b11011011 '
1$
#1820105
0$
#1824270
b11011100 '
1$
#1828435
0$
#1832600
b11011101 '
1$
#1836765
0$
#1840930
b11011110 '
1$
#1845095
0$
#1849260
b11011111 '
1$
#1853425
0$
#1857590
b11100000 '
1$
#1861755
0$
#1865920
b11100001 '
1$
#1870085
0$
#1874250
b11100010 '
1$
#1878415
0$
#1882580
b11100011 '
1$
#1886745
0$
#1890910
b11100100 '
1$
#1895075
0$
#1899240
b11100101 '
1$
#1903405
0$
#1907570
b11100110 '
1$
#1911735
0$
#1915900
b11100111 '
1$
#1920065
0$
#1924230
b11101000 '
1$
#1928395
0$
#1932560
b11101001 '
1$
#1936725
0$
#1940890
b11101010 '
1$
#1945055
0$
#1949220
b11101011 '
1$
#1953385
0$
#1957550
b11101100 '
1$
#1961715
0$
#1965880
b11101101 '
1$
#1970045
0$
#1974210
b11101110 '
1$
#1978375
0$
#1982540
b11101111 '
1$
#1986705
0$
#1990870
b11110000 '
1$
#1995035
0$
#1999200
b11110001 '
1$
#2003365
0$
#2007530
b11110010 '
1$
#2011695
0$
#2015860
b11110011 '
1$
#2020025
0$
#2024190
b11110100 '
1$
#2028355
0$
#2032520
b11110101 '
1$
#2036685
0$
#2040850
b11110110 '
1$
#2045015
0$
#2049180
b11110111 '
1$
#2053345
0$
#2057510
b11111000 '
1$
#2061675
0$
#2065840
b11111001 '
1$
#2070005
0$
#2074170
b11111010 '
1$
#2078335
0$
#2082500
b11111011 '
1$
#2086665
0$
#2090830
b11111100 '
1$
#2094995
0$
#2099160
b11111101 '
1$
#2103325
0$
#2107490
b11111110 '
1$
#2111655
0$
#2115820
b11111111 '
1$
#2119985
0$
#2124150
b100000000 '
1$
#2128315
0$
#2132480
b100000001 '
1$
#2136645
0$
#2140810
b100000010 '
1$
#2144975
0$
#2149140
b100000011 '
1$
#2153305
0$
#2157470
b100000100 '
1$
#2161635
0$
#2165800
b100000101 '
1$
#2169965
0$
#2174130
b100000110 '
1$
#2178295
0$
#2182460
b100000111 '
1$
#2186625
0$
#2190790
b100001000 '
1$
#2194955
0$
#2199120
b100001001 '
1$
#2203285
0$
#2207450
b100001010 '
1$
#2211615
0$
#2215780
b100001011 '
1$
#2219945
0$
#2224110
b100001100 '
1$
#2228275
0$
#2232440
b100001101 '
1$
#2236605
0$
#2240770
b100001110 '
1$
#2244935
0$
#2249100
b100001111 '
1$
#2253265
0$
#2257430
b100010000 '
1$
#2261595
0$
#2265760
b100010001 '
1$
#2269925
0$
#2274090
b100010010 '
1$
#2278255
0$
#2282420
b100010011 '
1$
#2286585
0$
#2290750
b100010100 '
1$
#2294915
0$
#2299080
b100010101 '
1$
#2303245
0$
#2307410
b100010110 '
1$
#2311575
0$
#2315740
b100010111 '
1$
#2319905
0$
#2324070
b100011000 '
1$
#2328235
0$
#2332400
b100011001 '
1$
#2336565
0$
#2340730
b100011010 '
1$
#2344895
0$
#2349060
b100011011 '
1$
#2353225
0$
#2357390
b100011100 '
1$
#2361555
0$
#2365720
b100011101 '
1$
#2369885
0$
#2374050
b100011110 '
1$
#2378215
0$
#2382380
b100011111 '
1$
#2386545
0$
#2390710
b100100000 '
1$
#2394875
0$
#2399040
b100100001 '
1$
#2403205
0$
#2407370
b100100010 '
1$
#2411535
0$
#2415700
b100100011 '
1$
#2419865
0$
#2424030
b100100100 '
1$
#2428195
0$
#2432360
b100100101 '
1$
#2436525
0$
#2440690
b100100110 '
1$
#2444855
0$
#2449020
b100100111 '
1$
#2453185
0$
#2457350
b100101000 '
1$
#2461515
0$
#2465680
b100101001 '
1$
#2469845
0$
#2474010
b100101010 '
1$
#2478175
0$
#2482340
b100101011 '
1$
#2486505
0$
#2490670
b100101100 '
1$
#2494835
0$
#2499000
b100101101 '
1$
#2503165
0$
#2507330
b100101110 '
1$
#2511495
0$
#2515660
b100101111 '
1$
#2519825
0$
#2523990
b100110000 '
1$
#2528155
0$
#2532320
b100110001 '
1$
#2536485
0$
#2540650
b100110010 '
1$
#2544815
0$
#2548980
b100110011 '
1$
#2553145
0$
#2557310
b100110100 '
1$
#2561475
0$
#2565640
b100110101 '
1$
#2569805
0$
#2573970
b100110110 '
1$
#2578135
0$
#2582300
b100110111 '
1$
#2586465
0$
#2590630
b100111000 '
1$
#2594795
0$
#2598960
b100111001 '
1$
#2603125
0$
#2607290
b100111010 '
1$
#2611455
0$
#2615620
b100111011 '
1$
#2619785
0$
#2623950
b100111100 '
1$
#2628115
0$
#2632280
b100111101 '
1$
#2636445
0$
#2640610
b100111110 '
1$
#2644775
0$
#2648940
b100111111 '
1$
#2653105
0$
#2657270
b101000000 '
1$
#2661435
0$
#2665600
b101000001 '
1$
#2669765
0$
#2673930
b101000010 '
1$
#2678095
0$
#2682260
b101000011 '
1$
#2686425
0$
#2690590
b101000100 '
1$
#2694755
0$
#2698920
b101000101 '
1$
#2703085
0$
#2707250
b101000110 '
1$
#2711415
0$
#2715580
b101000111 '
1$
#2719745
0$
#2723910
b101001000 '
1$
#2728075
0$
#2732240
b101001001 '
1$
#2736405
0$
#2740570
b101001010 '
1$
#2744735
0$
#2748900
b101001011 '
1$
#2753065
0$
#2757230
b101001100 '
1$
#2761395
0$
#2765560
b101001101 '
1$
#2769725
0$
#2773890
b101001110 '
1$
#2778055
0$
#2782220
b101001111 '
1$
#2786385
0$
#2790550
b101010000 '
1$
#2794715
0$
#2798880
b101010001 '
1$
#2803045
0$
#2807210
b101010010 '
1$
#2811375
0$
#2815540
b101010011 '
1$
#2819705
0$
#2823870
b101010100 '
1$
#2828035
0$
#2832200
b101010101 '
1$
#2836365
0$
#2840530
b101010110 '
1$
#2844695
0$
#2848860
b101010111 '
1$
#2853025
0$
#2857190
b101011000 '
1$
#2861355
0$
#2865520
b101011001 '
1$
#2869685
0$
#2873850
b101011010 '
1$
#2878015
0$
#2882180
b101011011 '
1$
#2886345
0$
#2890510
b101011100 '
1$
#2894675
0$
#2898840
b101011101 '
1$
#2903005
0$
#2907170
b101011110 '
1$
#2911335
0$
#2915500
b101011111 '
1$
#2919665
0$
#2923830
b101100000 '
1$
#2927995
0$
#2932160
b101100001 '
1$
#2936325
0$
#2940490
b101100010 '
1$
#2944655
0$
#2948820
b101100011 '
1$
#2952985
0$
#2957150
b101100100 '
1$
#2961315
0$
#2965480
b101100101 '
1$
#2969645
0$
#2973810
b101100110 '
1$
#2977975
0$
#2982140
b101100111 '
1$
#2986305
0$
#2990470
b101101000 '
1$
#2994635
0$
#2998800
b101101001 '
1$
#3002965
0$
#3007130
b101101010 '
1$
#3011295
0$
#3015460
b101101011 '
1$
#3019625
0$
#3023790
b101101100 '
1$
#3027955
0$
#3032120
b101101101 '
1$
#3036285
0$
#3040450
b101101110 '
1$
#3044615
0$
#3048780
b101101111 '
1$
#3052945
0$
#3057110
b101110000 '
1$
#3061275
0$
#3065440
b101110001 '
1$
#3069605
0$
#3073770
b101110010 '
1$
#3077935
0$
#3082100
b101110011 '
1$
#3086265
0$
#3090430
b101110100 '
1$
#3094595
0$
#3098760
b101110101 '
1$
#3102925
0$
#3107090
b101110110 '
1$
#3111255
0$
#3115420
b101110111 '
1$
#3119585
0$
#3123750
b101111000 '
1$
#3127915
0$
#3132080
b101111001 '
1$
#3136245
0$
#3140410
b101111010 '
1$
#3144575
0$
#3148740
b101111011 '
1$
#3152905
0$
#3157070
b101111100 '
1$
#3161235
0$
#3165400
b101111101 '
1$
#3169565
0$
#3173730
b101111110 '
1$
#3177895
0$
#3182060
b101111111 '
1$
#3186225
0$
#3190390
b110000000 '
1$
#3194555
0$
#3198720
b110000001 '
1$
#3202885
0$
#3207050
b110000010 '
1$
#3211215
0$
#3215380
b110000011 '
1$
#3219545
0$
#3223710
b110000100 '
1$
#3227875
0$
#3232040
b110000101 '
1$
#3236205
0$
#3240370
b110000110 '
1$
#3244535
0$
#3248700
b110000111 '
1$
#3252865
0$
#3257030
b110001000 '
1$
#3261195
0$
#3265360
b110001001 '
1$
#3269525
0$
#3273690
b110001010 '
1$
#3277855
0$
#3282020
b110001011 '
1$
#3286185
0$
#3290350
b110001100 '
1$
#3294515
0$
#3298680
b110001101 '
1$
#3302845
0$
#3307010
b110001110 '
1$
#3311175
0$
#3315340
b110001111 '
1$
#3319505
0$
#3323670
b110010000 '
1$
#3327835
0$
#3332000
b110010001 '
1$
#3336165
0$
#3340330
b110010010 '
1$
#3344495
0$
#3348660
b110010011 '
1$
#3352825
0$
#3356990
b110010100 '
1$
#3361155
0$
#3365320
b110010101 '
1$
#3369485
0$
#3373650
b110010110 '
1$
#3377815
0$
#3381980
b110010111 '
1$
#3386145
0$
#3390310
b110011000 '
1$
#3394475
0$
#3398640
b110011001 '
1$
#3402805
0$
#3406970
b110011010 '
1$
#3411135
0$
#3415300
b110011011 '
1$
#3419465
0$
#3423630
b110011100 '
1$
#3427795
0$
#3431960
b110011101 '
1$
#3436125
0$
#3440290
b110011110 '
1$
#3444455
0$
#3448620
b110011111 '
1$
#3452785
0$
#3456950
b110100000 '
1$
#3461115
0$
#3465280
b110100001 '
1$
#3469445
0$
#3473610
b110100010 '
1$
#3477775
0$
#3481940
b110100011 '
1$
#3486105
0$
#3490270
b110100100 '
1$
#3494435
0$
#3498600
b110100101 '
1$
#3502765
0$
#3506930
b110100110 '
1$
#3511095
0$
#3515260
b110100111 '
1$
#3519425
0$
#3523590
b110101000 '
1$
#3527755
0$
#3531920
b110101001 '
1$
#3536085
0$
#3540250
b110101010 '
1$
#3544415
0$
#3548580
b110101011 '
1$
#3552745
0$
#3556910
b110101100 '
1$
#3561075
0$
#3565240
b110101101 '
1$
#3569405
0$
#3573570
b110101110 '
1$
#3577735
0$
#3581900
b110101111 '
1$
#3586065
0$
#3590230
b110110000 '
1$
#3594395
0$
#3598560
b110110001 '
1$
#3602725
0$
#3606890
b110110010 '
1$
#3611055
0$
#3615220
b110110011 '
1$
#3619385
0$
#3623550
b110110100 '
1$
#3627715
0$
#3631880
b110110101 '
1$
#3636045
0$
#3640210
b110110110 '
1$
#3644375
0$
#3648540
b110110111 '
1$
#3652705
0$
#3656870
b110111000 '
1$
#3661035
0$
#3665200
b110111001 '
1$
#3669365
0$
#3673530
b110111010 '
1$
#3677695
0$
#3681860
b110111011 '
1$
#3686025
0$
#3690190
b110111100 '
1$
#3694355
0$
#3698520
b110111101 '
1$
#3702685
0$
#3706850
b110111110 '
1$
#3711015
0$
#3715180
b110111111 '
1$
#3719345
0$
#3723510
b111000000 '
1$
#3727675
0$
#3731840
b111000001 '
1$
#3736005
0$
#3740170
b111000010 '
1$
#3744335
0$
#3748500
b111000011 '
1$
#3752665
0$
#3756830
b111000100 '
1$
#3760995
0$
#3765160
b111000101 '
1$
#3769325
0$
#3773490
b111000110 '
1$
#3777655
0$
#3781820
b111000111 '
1$
#3785985
0$
#3790150
b111001000 '
1$
#3794315
0$
#3798480
b111001001 '
1$
#3802645
0$
#3806810
b111001010 '
1$
#3810975
0$
#3815140
b111001011 '
1$
#3819305
0$
#3823470
b111001100 '
1$
#3827635
0$
#3831800
b111001101 '
1$
#3835965
0$
#3840130
b111001110 '
1$
#3844295
0$
#3848460
b111001111 '
1$
#3852625
0$
#3856790
b111010000 '
1$
#3860955
0$
#3865120
b111010001 '
1$
#3869285
0$
#3873450
b111010010 '
1$
#3877615
0$
#3881780
b111010011 '
1$
#3885945
0$
#3890110
b111010100 '
1$
#3894275
0$
#3898440
b111010101 '
1$
#3902605
0$
#3906770
b111010110 '
1$
#3910935
0$
#3915100
b111010111 '
1$
#3919265
0$
#3923430
b111011000 '
1$
#3927595
0$
#3931760
b111011001 '
1$
#3935925
0$
#3940090
b111011010 '
1$
#3944255
0$
#3948420
b111011011 '
1$
#3952585
0$
#3956750
b111011100 '
1$
#3960915
0$
#3965080
b111011101 '
1$
#3969245
0$
#3973410
b111011110 '
1$
#3977575
0$
#3981740
b111011111 '
1$
#3985905
0$
#3990070
b111100000 '
1$
#3994235
0$
#3998400
b111100001 '
1$
#4002565
0$
#4006730
b111100010 '
1$
#4010895
0$
#4015060
b111100011 '
1$
#4019225
0$
#4023390
b111100100 '
1$
#4027555
0$
#4031720
b111100101 '
1$
#4035885
0$
#4040050
b111100110 '
1$
#4044215
0$
#4048380
b111100111 '
1$
#4052545
0$
#4056710
b111101000 '
1$
#4060875
0$
#4065040
b111101001 '
1$
#4069205
0$
#4073370
b111101010 '
1$
#4077535
0$
#4081700
b111101011 '
1$
#4085865
0$
#4090030
b111101100 '
1$
#4094195
0$
#4098360
b111101101 '
1$
#4102525
0$
#4106690
b111101110 '
1$
#4110855
0$
#4115020
b111101111 '
1$
#4119185
0$
#4123350
b111110000 '
1$
#4127515
0$
#4131680
b111110001 '
1$
#4135845
0$
#4140010
b111110010 '
1$
#4144175
0$
#4148340
b111110011 '
1$
#4152505
0$
#4156670
b111110100 '
1$
#4160835
0$
#4165000
b111110101 '
1$
#4169165
0$
#4173330
b111110110 '
1$
#4177495
0$
#4181660
b111110111 '
1$
#4185825
0$
#4189990
b111111000 '
1$
#4194155
0$
#4198320
b111111001 '
1$
#4202485
0$
#4206650
b111111010 '
1$
#4210815
0$
#4214980
b111111011 '
1$
#4219145
0$
#4223310
b111111100 '
1$
#4227475
0$
#4231640
b111111101 '
1$
#4235805
0$
#4239970
b111111110 '
1$
#4244135
0$
#4248300
b111111111 '
1$
#4252465
0$
#4256630
b1000000000 '
1$
#4260795
0$
#4264960
b1000000001 '
1$
#4269125
0$
#4273290
b1000000010 '
1$
#4277455
0$
#4281620
b1000000011 '
1$
#4285785
0$
#4289950
b1000000100 '
1$
#4294115
0$
#4298280
b1000000101 '
1$
#4302445
0$
#4306610
b1000000110 '
1$
#4310775
0$
#4314940
b1000000111 '
1$
#4319105
0$
#4323270
b1000001000 '
1$
#4327435
0$
#4331600
b1000001001 '
1$
#4335765
0$
#4339930
b1000001010 '
1$
#4344095
0$
#4348260
b1000001011 '
1$
#4352425
0$
#4356590
b1000001100 '
1$
#4360755
0$
#4364920
b1000001101 '
1$
#4369085
0$
#4373250
b1000001110 '
1$
#4377415
0$
#4381580
b1000001111 '
1$
#4385745
0$
#4389910
b1000010000 '
1$
#4394075
0$
#4398240
b1000010001 '
1$
#4402405
0$
#4406570
b1000010010 '
1$
#4410735
0$
#4414900
b1000010011 '
1$
#4419065
0$
#4423230
b1000010100 '
1$
#4427395
0$
#4431560
b1000010101 '
1$
#4435725
0$
#4439890
b1000010110 '
1$
#4444055
0$
#4448220
b1000010111 '
1$
#4452385
0$
#4456550
b1000011000 '
1$
#4460715
0$
#4464880
b1000011001 '
1$
#4469045
0$
#4473210
b1000011010 '
1$
#4477375
0$
#4481540
b1000011011 '
1$
#4485705
0$
#4489870
b1000011100 '
1$
#4494035
0$
#4498200
b1000011101 '
1$
#4502365
0$
#4506530
b1000011110 '
1$
#4510695
0$
#4514860
b1000011111 '
1$
#4519025
0$
#4523190
b1000100000 '
1$
#4527355
0$
#4531520
b1000100001 '
1$
#4535685
0$
#4539850
b1000100010 '
1$
#4544015
0$
#4548180
b1000100011 '
1$
#4552345
0$
#4556510
b1000100100 '
1$
#4560675
0$
#4564840
b1000100101 '
1$
#4569005
0$
#4573170
b1000100110 '
1$
#4577335
0$
#4581500
b1000100111 '
1$
#4585665
0$
#4589830
b1000101000 '
1$
#4593995
0$
#4598160
b1000101001 '
1$
#4602325
0$
#4606490
b1000101010 '
1$
#4610655
0$
#4614820
b1000101011 '
1$
#4618985
0$
#4623150
b1000101100 '
1$
#4627315
0$
#4631480
b1000101101 '
1$
#4635645
0$
#4639810
b1000101110 '
1$
#4643975
0$
#4648140
b1000101111 '
1$
#4652305
0$
#4656470
b1000110000 '
1$
#4660635
0$
#4664800
b1000110001 '
1$
#4668965
0$
#4673130
b1000110010 '
1$
#4677295
0$
#4681460
b1000110011 '
1$
#4685625
0$
#4689790
b1000110100 '
1$
#4693955
0$
#4698120
b1000110101 '
1$
#4702285
0$
#4706450
b1000110110 '
1$
#4710615
0$
#4714780
b1000110111 '
1$
#4718945
0$
#4723110
b1000111000 '
1$
#4727275
0$
#4731440
b1000111001 '
1$
#4735605
0$
#4739770
b1000111010 '
1$
#4743935
0$
#4748100
b1000111011 '
1$
#4752265
0$
#4756430
b1000111100 '
1$
#4760595
0$
#4764760
b1000111101 '
1$
#4768925
0$
#4773090
b1000111110 '
1$
#4777255
0$
#4781420
b1000111111 '
1$
#4785585
0$
#4789750
b1001000000 '
1$
#4793915
0$
#4798080
b1001000001 '
1$
#4802245
0$
#4806410
b1001000010 '
1$
#4810575
0$
#4814740
b1001000011 '
1$
#4818905
0$
#4823070
b1001000100 '
1$
#4827235
0$
#4831400
b1001000101 '
1$
#4835565
0$
#4839730
b1001000110 '
1$
#4843895
0$
#4848060
b1001000111 '
1$
#4852225
0$
#4856390
b1001001000 '
1$
#4860555
0$
#4864720
b1001001001 '
1$
#4868885
0$
#4873050
b1001001010 '
1$
#4877215
0$
#4881380
b1001001011 '
1$
#4885545
0$
#4889710
b1001001100 '
1$
#4893875
0$
#4898040
b1001001101 '
1$
#4902205
0$
#4906370
b1001001110 '
1$
#4910535
0$
#4914700
b1001001111 '
1$
#4918865
0$
#4923030
b1001010000 '
1$
#4927195
0$
#4931360
b1001010001 '
1$
#4935525
0$
#4939690
b1001010010 '
1$
#4943855
0$
#4948020
b1001010011 '
1$
#4952185
0$
#4956350
b1001010100 '
1$
#4960515
0$
#4964680
b1001010101 '
1$
#4968845
0$
#4973010
b1001010110 '
1$
#4977175
0$
#4981340
b1001010111 '
1$
#4985505
0$
#4989670
b1001011000 '
1$
#4993835
0$
#4998000
b1001011001 '
1$
#5002165
0$
#5006330
b1001011010 '
1$
#5010495
0$
#5014660
b1001011011 '
1$
#5018825
0$
#5022990
b1001011100 '
1$
#5027155
0$
#5031320
b1001011101 '
1$
#5035485
0$
#5039650
b1001011110 '
1$
#5043815
0$
#5047980
b1001011111 '
1$
#5052145
0$
#5056310
b1001100000 '
1$
#5060475
0$
#5064640
b1001100001 '
1$
#5068805
0$
#5072970
b1001100010 '
1$
#5077135
0$
#5081300
b1001100011 '
1$
#5085465
0$
#5089630
b1001100100 '
1$
#5093795
0$
#5097960
b1001100101 '
1$
#5102125
0$
#5106290
b1001100110 '
1$
#5110455
0$
#5114620
b1001100111 '
1$
#5118785
0$
#5122950
b1001101000 '
1$
#5127115
0$
#5131280
b1001101001 '
1$
#5135445
0$
#5139610
b1001101010 '
1$
#5143775
0$
#5147940
b1001101011 '
1$
#5152105
0$
#5156270
b1001101100 '
1$
#5160435
0$
#5164600
b1001101101 '
1$
#5168765
0$
#5172930
b1001101110 '
1$
#5177095
0$
#5181260
b1001101111 '
1$
#5185425
0$
